vedro_import_profiler/__init__.py
vedro_import_profiler/_import_profiler_plugin.py
vedro_import_profiler/_scenario_file_loader.py
vedro_import_profiler/py.typed
vedro_import_profiler-0.0.2.dist-info/LICENSE
vedro_import_profiler-0.0.2.dist-info/METADATA
vedro_import_profiler-0.0.2.dist-info/WHEEL
vedro_import_profiler-0.0.2.dist-info/top_level.txt
vedro_import_profiler-0.0.2.dist-info/RECORD
