Metadata-Version: 2.1
Name: vedro-import-profiler
Version: 0.0.2
Summary: Import profiler for Vedro framework
Home-page: https://github.com/vedro-universe/vedro-import-profiler
Author: Nikita Tsvetkov
Author-email: tsv1@fastmail.com
License: Apache-2.0
Project-URL: GitHub, https://github.com/vedro-universe/vedro-import-profiler
Classifier: License :: OSI Approved :: Apache Software License
Classifier: Programming Language :: Python :: 3.8
Classifier: Programming Language :: Python :: 3.9
Classifier: Programming Language :: Python :: 3.10
Classifier: Programming Language :: Python :: 3.11
Classifier: Programming Language :: Python :: 3.12
Classifier: Typing :: Typed
Requires-Python: >=3.8
License-File: LICENSE
Requires-Dist: vedro <2.0,>=1.11
